LICENSE
README.md
setup.py
Oikos.egg-info/PKG-INFO
Oikos.egg-info/SOURCES.txt
Oikos.egg-info/dependency_links.txt
Oikos.egg-info/requires.txt
Oikos.egg-info/top_level.txt
oikos/__init__.py
oikos.egg-info/PKG-INFO
oikos.egg-info/SOURCES.txt
oikos.egg-info/dependency_links.txt
oikos.egg-info/requires.txt
oikos.egg-info/top_level.txt
oikos/macroeconomia/__init__.py
oikos/macroeconomia/crecimiento.py
oikos/macroeconomia/dinero.py
oikos/macroeconomia/economia_abierta.py
oikos/macroeconomia/islm.py
oikos/macroeconomia/monetaria.py
oikos/macroeconomia/oada.py
oikos/mediciones/__init__.py
oikos/mediciones/desigualdad.py
oikos/microeconomia/__init__.py
oikos/microeconomia/bienestar.py
oikos/microeconomia/comercio.py
oikos/microeconomia/competencia.py
oikos/microeconomia/consumidor.py
oikos/microeconomia/mercado.py
oikos/microeconomia/productor.py
oikos/nucleo/__init__.py
oikos/nucleo/base.py
oikos/nucleo/excepciones.py
oikos/utilidades/__init__.py
oikos/utilidades/decoradores.py
oikos/utilidades/parseador.py
oikos/utilidades/validadores.py
oikos/utilidades/visuales.py