Metadata-Version: 2.4
Name: oikos
Version: 0.3.1
Summary: Biblioteca para modelos económicos en Python.
Home-page: https://github.com/marcosjuniorhernandez/economy
Author: Marcos Junior Hernández-Moreno
Author-email: iam.marcoshernandez@gmail.com
Project-URL: Documentation, https://oikos.readthedocs.io/en/latest/
Project-URL: Source, https://github.com/marcosjuniorhernandez/economy
Keywords: economics,macroeconomics,economic-modeling,symbolic-math,economic-theory,education
Classifier: Programming Language :: Python :: 3
Classifier: Programming Language :: Python :: 3 :: Only
Classifier: Intended Audience :: Education
Classifier: Intended Audience :: Science/Research
Classifier: Topic :: Scientific/Engineering
Classifier: Topic :: Scientific/Engineering :: Mathematics
Classifier: License :: OSI Approved :: MIT License
Requires-Python: >=3.8
License-File: LICENSE
Requires-Dist: numpy
Requires-Dist: sympy
Requires-Dist: scipy
Requires-Dist: latex2sympy2
Requires-Dist: ipython
Requires-Dist: matplotlib
Requires-Dist: rich
Dynamic: author
Dynamic: author-email
Dynamic: classifier
Dynamic: description
Dynamic: description-content-type
Dynamic: home-page
Dynamic: keywords
Dynamic: license-file
Dynamic: project-url
Dynamic: requires-dist
Dynamic: requires-python
Dynamic: summary
